Metadata-Version: 2.1
Name: deuces-numpy
Version: 0.5
Summary: 
